{"result":0,"resultDesc":"Success","requestId":0,"data":{"page_info":{"page_idx":1,"page_size":10,"total_record":269395,"total_page":26940,"begin_idx":1,"end_idx":10},"items":[{"drawCode":"0271582","openDate":"23/02/2026 21:52:00","num1":"1","num2":"8","num3":"13","num4":"16","num5":"19","num6":"24","num7":"26","num8":"30","num9":"32","num10":"36","num11":"38","num12":"44","num13":"46","num14":"51","num15":"57","num16":"61","num17":"62","num18":"66","num19":"70","num20":"77","numEven":"13","numOdd":"7","numUpper":"9","numLower":"11","evenStatusWin":1,"oddStatusWin":0,"upperStatusWin":0,"lowerStatusWin":1,"even1112StatusWin":0,"odd1112StatusWin":0,"evenOddStatusWin":0,"upperLowerStatusWin":0},{"drawCode":"0271581","openDate":"23/02/2026 21:44:00","num1":"2","num2":"3","num3":"8","num4":"11","num5":"16","num6":"19","num7":"24","num8":"32","num9":"35","num10":"41","num11":"46","num12":"47","num13":"51","num14":"67","num15":"69","num16":"70","num17":"73","num18":"74","num19":"75","num20":"80","numEven":"9","numOdd":"11","numUpper":"11","numLower":"9","evenStatusWin":0,"oddStatusWin":0,"upperStatusWin":1,"lowerStatusWin":0,"even1112StatusWin":0,"odd1112StatusWin":1,"evenOddStatusWin":0,"upperLowerStatusWin":0},{"drawCode":"0271580","openDate":"23/02/2026 21:36:00","num1":"1","num2":"6","num3":"8","num4":"21","num5":"22","num6":"26","num7":"28","num8":"35","num9":"42","num10":"45","num11":"53","num12":"61","num13":"64","num14":"67","num15":"68","num16":"72","num17":"73","num18":"74","num19":"75","num20":"80","numEven":"11","numOdd":"9","numUpper":"12","numLower":"8","evenStatusWin":0,"oddStatusWin":0,"upperStatusWin":1,"lowerStatusWin":0,"even1112StatusWin":1,"odd1112StatusWin":0,"evenOddStatusWin":0,"upperLowerStatusWin":0},{"drawCode":"0271579","openDate":"23/02/2026 21:28:00","num1":"2","num2":"3","num3":"11","num4":"15","num5":"21","num6":"23","num7":"26","num8":"33","num9":"38","num10":"41","num11":"43","num12":"48","num13":"52","num14":"58","num15":"61","num16":"63","num17":"64","num18":"71","num19":"75","num20":"76","numEven":"8","numOdd":"12","numUpper":"11","numLower":"9","evenStatusWin":0,"oddStatusWin":0,"upperStatusWin":1,"lowerStatusWin":0,"even1112StatusWin":0,"odd1112StatusWin":1,"evenOddStatusWin":0,"upperLowerStatusWin":0},{"drawCode":"0271578","openDate":"23/02/2026 21:20:00","num1":"1","num2":"2","num3":"3","num4":"13","num5":"16","num6":"23","num7":"31","num8":"33","num9":"34","num10":"40","num11":"42","num12":"54","num13":"59","num14":"64","num15":"65","num16":"69","num17":"71","num18":"72","num19":"74","num20":"79","numEven":"9","numOdd":"11","numUpper":"10","numLower":"10","evenStatusWin":0,"oddStatusWin":0,"upperStatusWin":0,"lowerStatusWin":0,"even1112StatusWin":0,"odd1112StatusWin":1,"evenOddStatusWin":1,"upperLowerStatusWin":0},{"drawCode":"0271577","openDate":"23/02/2026 21:12:00","num1":"2","num2":"7","num3":"13","num4":"14","num5":"15","num6":"19","num7":"28","num8":"36","num9":"37","num10":"43","num11":"44","num12":"48","num13":"58","num14":"59","num15":"61","num16":"65","num17":"68","num18":"69","num19":"75","num20":"76","numEven":"9","numOdd":"11","numUpper":"11","numLower":"9","evenStatusWin":0,"oddStatusWin":0,"upperStatusWin":1,"lowerStatusWin":0,"even1112StatusWin":0,"odd1112StatusWin":1,"evenOddStatusWin":0,"upperLowerStatusWin":0},{"drawCode":"0271576","openDate":"23/02/2026 21:04:00","num1":"8","num2":"9","num3":"15","num4":"18","num5":"19","num6":"21","num7":"24","num8":"40","num9":"42","num10":"49","num11":"50","num12":"53","num13":"61","num14":"62","num15":"63","num16":"64","num17":"73","num18":"76","num19":"77","num20":"79","numEven":"9","numOdd":"11","numUpper":"12","numLower":"8","evenStatusWin":0,"oddStatusWin":0,"upperStatusWin":1,"lowerStatusWin":0,"even1112StatusWin":0,"odd1112StatusWin":1,"evenOddStatusWin":0,"upperLowerStatusWin":0},{"drawCode":"0271575","openDate":"23/02/2026 20:56:00","num1":"2","num2":"5","num3":"10","num4":"11","num5":"14","num6":"16","num7":"17","num8":"20","num9":"31","num10":"34","num11":"40","num12":"42","num13":"43","num14":"44","num15":"51","num16":"55","num17":"61","num18":"63","num19":"64","num20":"70","numEven":"11","numOdd":"9","numUpper":"9","numLower":"11","evenStatusWin":0,"oddStatusWin":0,"upperStatusWin":0,"lowerStatusWin":1,"even1112StatusWin":1,"odd1112StatusWin":0,"evenOddStatusWin":0,"upperLowerStatusWin":0},{"drawCode":"0271574","openDate":"23/02/2026 20:48:00","num1":"1","num2":"9","num3":"11","num4":"22","num5":"23","num6":"26","num7":"27","num8":"35","num9":"36","num10":"37","num11":"38","num12":"40","num13":"45","num14":"53","num15":"57","num16":"58","num17":"60","num18":"61","num19":"71","num20":"74","numEven":"8","numOdd":"12","numUpper":"8","numLower":"12","evenStatusWin":0,"oddStatusWin":0,"upperStatusWin":0,"lowerStatusWin":1,"even1112StatusWin":0,"odd1112StatusWin":1,"evenOddStatusWin":0,"upperLowerStatusWin":0},{"drawCode":"0271573","openDate":"23/02/2026 20:40:00","num1":"1","num2":"4","num3":"7","num4":"11","num5":"23","num6":"24","num7":"31","num8":"32","num9":"34","num10":"35","num11":"38","num12":"41","num13":"43","num14":"50","num15":"53","num16":"55","num17":"65","num18":"67","num19":"74","num20":"78","numEven":"8","numOdd":"12","numUpper":"9","numLower":"11","evenStatusWin":0,"oddStatusWin":0,"upperStatusWin":0,"lowerStatusWin":1,"even1112StatusWin":0,"odd1112StatusWin":1,"evenOddStatusWin":0,"upperLowerStatusWin":0}]}}